{
  "android-instant": {
    "REMOTE_SERVER_ROOT": "",
    "host": "",
    "pathPattern": "",
    "recordPath": "",
    "scheme": "https",
    "skipRecord": false
  },
  "appKey": "",
  "appSecret": "",
  "encryptJs": false,
  "excludeScenes": [],
  "fb-instant-games": {},
  "includeAnySDK": false,
  "includeSDKBox": false,
  "inlineSpriteFrames": true,
  "inlineSpriteFrames_native": true,
  "jailbreakPlatform": false,
  "md5Cache": false,
  "mergeStartScene": false,
  "oauthLoginServer": "",
  "optimizeHotUpdate": true,
  "orientation": {
    "landscapeLeft": true,
    "landscapeRight": true,
    "portrait": false,
    "upsideDown": false
  },
  "packageName": "org.cocos2d.doudizhu",
  "privateKey": "",
  "qqplay": {
    "REMOTE_SERVER_ROOT": "",
    "orientation": "portrait"
  },
  "startScene": "001e8c75-bbec-4aa8-99fc-589f636a8ac6",
  "title": "doudizhu",
  "webOrientation": "auto",
  "wechatgame": {
    "REMOTE_SERVER_ROOT": "",
    "appid": "wx6ac3f5090a6b99c5",
    "orientation": "portrait",
    "subContext": ""
  },
  "xxteaKey": "3fdc3133-d0b7-43",
  "zipCompressJs": true
}